{
	"createdDate": "2023-03-25T18:03:47.036969449Z",
	"endDate": "2023-03-25T18:08:18.922268291Z",
	"id": "report",
	"intensities": {
		"asia": 0,
		"asiapacific": 0,
		"australia": 0,
		"australiacentral": 785.1683924700001,
		"australiacentral2": 785.1683924700001,
		"australiaeast": 785.1683924700001,
		"australiasoutheast": 716.2223522300001,
		"brazil": 0,
		"brazilsouth": 0,
		"brazilsoutheast": 0,
		"canada": 0,
		"canadacentral": 461.75703266000005,
		"canadaeast": 443.61333786,
		"centralindia": 0,
		"centralus": 643.64757303,
		"centraluseuap": 643.64757303,
		"centralusstage": 0,
		"eastasia": 0,
		"eastasiastage": 0,
		"eastus": 571.9799785700001,
		"eastus2": 571.9799785700001,
		"eastus2euap": 571.9799785700001,
		"eastus2stage": 0,
		"eastusstage": 0,
		"europe": 0,
		"france": 0,
		"francecentral": 0,
		"francesouth": 0,
		"germany": 0,
		"germanynorth": 0,
		"germanywestcentral": 0,
		"global": 0,
		"india": 0,
		"japan": 0,
		"japaneast": 0,
		"japanwest": 0,
		"jioindiacentral": 0,
		"jioindiawest": 0,
		"korea": 0,
		"koreacentral": 0,
		"koreasouth": 0,
		"northcentralus": 571.9799785700001,
		"northcentralusstage": 0,
		"northeurope": 511.65219336,
		"norway": 550,
		"norwayeast": 0,
		"norwaywest": 0,
		"southafrica": 0,
		"southafricanorth": 0,
		"southafricawest": 0,
		"southcentralus": 542.49647452,
		"southcentralusstage": 0,
		"southeastasia": 0,
		"southeastasiastage": 0,
		"southindia": 0,
		"swedencentral": 0,
		"switzerland": 0,
		"switzerlandnorth": 0,
		"switzerlandwest": 0,
		"uae": 0,
		"uaecentral": 0,
		"uaenorth": 0,
		"uk": 0,
		"uksouth": 418.21216514,
		"ukwest": 418.21216514,
		"unitedstates": 0,
		"unitedstateseuap": 0,
		"westcentralus": 743.8914868,
		"westeurope": 0,
		"westindia": 0,
		"westus": 24.94758035,
		"westus2": 585.1341573000001,
		"westus2stage": 0,
		"westus3": 587.4021191500001,
		"westusstage": 0
	},
	"startDate": "2023-03-25T18:03:18.922268217Z",
	"userId": ""
}
