{
	"createdDate": "2022-11-02T15:33:43.358397607Z",
	"endDate": "2022-11-02T15:38:19.305848105Z",
	"id": "report",
	"intensities": {
		"asia": 0,
		"asiapacific": 0,
		"australia": 0,
		"australiacentral": 849.12491664,
		"australiacentral2": 849.12491664,
		"australiaeast": 849.12491664,
		"australiasoutheast": 825.99170577,
		"brazil": 0,
		"brazilsouth": 0,
		"brazilsoutheast": 0,
		"canada": 0,
		"canadacentral": 493.05490619,
		"canadaeast": 472.18965717000003,
		"centralindia": 0,
		"centralus": 677.21340841,
		"centraluseuap": 677.21340841,
		"centralusstage": 0,
		"eastasia": 0,
		"eastasiastage": 0,
		"eastus": 527.0743339400001,
		"eastus2": 527.0743339400001,
		"eastus2euap": 527.0743339400001,
		"eastus2stage": 0,
		"eastusstage": 0,
		"europe": 0,
		"france": 0,
		"francecentral": 0,
		"francesouth": 0,
		"germany": 0,
		"germanynorth": 0,
		"germanywestcentral": 0,
		"global": 0,
		"india": 0,
		"japan": 0,
		"japaneast": 0,
		"japanwest": 0,
		"jioindiacentral": 0,
		"jioindiawest": 0,
		"korea": 0,
		"koreacentral": 0,
		"koreasouth": 0,
		"northcentralus": 527.0743339400001,
		"northcentralusstage": 0,
		"northeurope": 584.22697256,
		"norway": 0,
		"norwayeast": 0,
		"norwaywest": 0,
		"southafrica": 0,
		"southafricanorth": 0,
		"southafricawest": 0,
		"southcentralus": 547.93958296,
		"southcentralusstage": 0,
		"southeastasia": 0,
		"southeastasiastage": 0,
		"southindia": 0,
		"swedencentral": 0,
		"switzerland": 0,
		"switzerlandnorth": 0,
		"switzerlandwest": 0,
		"uae": 0,
		"uaecentral": 0,
		"uaenorth": 0,
		"uk": 0,
		"uksouth": 442.70615312,
		"ukwest": 442.70615312,
		"unitedstates": 0,
		"unitedstateseuap": 0,
		"westcentralus": 730.2837157,
		"westeurope": 0,
		"westindia": 0,
		"westus": 433.18071335,
		"westus2": 554.28987614,
		"westus2stage": 0,
		"westus3": 472.64324954,
		"westusstage": 0
	},
	"startDate": "2022-11-02T15:33:19.305847991Z",
	"userId": ""
}
