{
	"createdDate": "2023-04-04T22:53:59.366668747Z",
	"endDate": "2023-04-04T22:58:25.394521024Z",
	"id": "report",
	"intensities": {
		"asia": 0,
		"asiapacific": 0,
		"australia": 0,
		"australiacentral": 833.24918369,
		"australiacentral2": 833.24918369,
		"australiaeast": 833.24918369,
		"australiasoutheast": 435.90226757000005,
		"brazil": 0,
		"brazilsouth": 0,
		"brazilsoutheast": 0,
		"canada": 0,
		"canadacentral": 513.01297047,
		"canadaeast": 483.52946642,
		"centralindia": 0,
		"centralus": 648.18349673,
		"centraluseuap": 648.18349673,
		"centralusstage": 0,
		"eastasia": 0,
		"eastasiastage": 0,
		"eastus": 574.70153279,
		"eastus2": 574.70153279,
		"eastus2euap": 574.70153279,
		"eastus2stage": 0,
		"eastusstage": 0,
		"europe": 0,
		"france": 0,
		"francecentral": 0,
		"francesouth": 0,
		"germany": 0,
		"germanynorth": 0,
		"germanywestcentral": 0,
		"global": 0,
		"india": 0,
		"japan": 0,
		"japaneast": 0,
		"japanwest": 0,
		"jioindiacentral": 0,
		"jioindiawest": 0,
		"korea": 0,
		"koreacentral": 0,
		"koreasouth": 0,
		"northcentralus": 574.70153279,
		"northcentralusstage": 0,
		"northeurope": 513.01297047,
		"norway": 438,
		"norwayeast": 0,
		"norwaywest": 0,
		"southafrica": 0,
		"southafricanorth": 0,
		"southafricawest": 0,
		"southcentralus": 550.20754481,
		"southcentralusstage": 0,
		"southeastasia": 0,
		"southeastasiastage": 0,
		"southindia": 0,
		"swedencentral": 0,
		"switzerland": 0,
		"switzerlandnorth": 0,
		"switzerlandwest": 0,
		"uae": 0,
		"uaecentral": 0,
		"uaenorth": 0,
		"uk": 0,
		"uksouth": 420.48012699000003,
		"ukwest": 420.48012699000003,
		"unitedstates": 0,
		"unitedstateseuap": 0,
		"westcentralus": 665.42000679,
		"westeurope": 0,
		"westindia": 0,
		"westus": 63.04933943,
		"westus2": 506.66267729000003,
		"westus2stage": 0,
		"westus3": 560.64016932,
		"westusstage": 0
	},
	"startDate": "2023-04-04T22:53:25.394520945Z",
	"userId": ""
}
