{
	"createdDate": "2023-04-21T17:03:45.306318835Z",
	"endDate": "2023-04-21T17:08:18.849569111Z",
	"id": "report",
	"intensities": {
		"asia": 0,
		"asiapacific": 0,
		"australia": 0,
		"australiacentral": 791.9722780200001,
		"australiacentral2": 791.9722780200001,
		"australiaeast": 791.9722780200001,
		"australiasoutheast": 710.32565142,
		"brazil": 0,
		"brazilsouth": 0,
		"brazilsoutheast": 0,
		"canada": 0,
		"canadacentral": 452.23159289,
		"canadaeast": 439.53100653,
		"centralindia": 0,
		"centralus": 502.58034596,
		"centraluseuap": 502.58034596,
		"centralusstage": 0,
		"eastasia": 0,
		"eastasiastage": 0,
		"eastus": 613.2568842400001,
		"eastus2": 613.2568842400001,
		"eastus2euap": 613.2568842400001,
		"eastus2stage": 0,
		"eastusstage": 0,
		"europe": 0,
		"france": 0,
		"francecentral": 0,
		"francesouth": 0,
		"germany": 0,
		"germanynorth": 0,
		"germanywestcentral": 0,
		"global": 0,
		"india": 0,
		"japan": 0,
		"japaneast": 0,
		"japanwest": 0,
		"jioindiacentral": 0,
		"jioindiawest": 0,
		"korea": 0,
		"koreacentral": 0,
		"koreasouth": 0,
		"northcentralus": 613.2568842400001,
		"northcentralusstage": 0,
		"northeurope": 462.21062503,
		"norway": 464,
		"norwayeast": 0,
		"norwaywest": 0,
		"southafrica": 0,
		"southafricanorth": 0,
		"southafricawest": 0,
		"southcentralus": 547.48599059,
		"southcentralusstage": 0,
		"southeastasia": 0,
		"southeastasiastage": 0,
		"southindia": 0,
		"swedencentral": 0,
		"switzerland": 0,
		"switzerlandnorth": 0,
		"switzerlandwest": 0,
		"uae": 0,
		"uaecentral": 0,
		"uaenorth": 0,
		"uk": 0,
		"uksouth": 466.74654873000003,
		"ukwest": 466.74654873000003,
		"unitedstates": 0,
		"unitedstateseuap": 0,
		"westcentralus": 675.3990389300001,
		"westeurope": 0,
		"westindia": 0,
		"westus": 23.586803240000002,
		"westus2": 519.36326365,
		"westus2stage": 0,
		"westus3": 551.11472955,
		"westusstage": 0
	},
	"startDate": "2023-04-21T17:03:18.849569037Z",
	"userId": ""
}
