{
	"createdDate": "2023-03-03T20:04:01.444522679Z",
	"endDate": "2023-03-03T20:08:32.134897275Z",
	"id": "report",
	"intensities": {
		"asia": 0,
		"asiapacific": 0,
		"australia": 0,
		"australiacentral": 832.3419989500001,
		"australiacentral2": 832.3419989500001,
		"australiaeast": 832.3419989500001,
		"australiasoutheast": 668.14156101,
		"brazil": 0,
		"brazilsouth": 0,
		"brazilsoutheast": 0,
		"canada": 0,
		"canadacentral": 476.72558087,
		"canadaeast": 465.83936399000004,
		"centralindia": 0,
		"centralus": 656.3481593900001,
		"centraluseuap": 656.3481593900001,
		"centralusstage": 0,
		"eastasia": 0,
		"eastasiastage": 0,
		"eastus": 576.5159022700001,
		"eastus2": 576.5159022700001,
		"eastus2euap": 576.5159022700001,
		"eastus2stage": 0,
		"eastusstage": 0,
		"europe": 0,
		"france": 0,
		"francecentral": 0,
		"francesouth": 0,
		"germany": 0,
		"germanynorth": 0,
		"germanywestcentral": 0,
		"global": 0,
		"india": 0,
		"japan": 0,
		"japaneast": 0,
		"japanwest": 0,
		"jioindiacentral": 0,
		"jioindiawest": 0,
		"korea": 0,
		"koreacentral": 0,
		"koreasouth": 0,
		"northcentralus": 576.5159022700001,
		"northcentralusstage": 0,
		"northeurope": 522.53841024,
		"norway": 0,
		"norwayeast": 0,
		"norwaywest": 0,
		"southafrica": 0,
		"southafricanorth": 0,
		"southafricawest": 0,
		"southcentralus": 558.37220747,
		"southcentralusstage": 0,
		"southeastasia": 0,
		"southeastasiastage": 0,
		"southindia": 0,
		"swedencentral": 0,
		"switzerland": 0,
		"switzerlandnorth": 0,
		"switzerlandwest": 0,
		"uae": 0,
		"uaecentral": 0,
		"uaenorth": 0,
		"uk": 0,
		"uksouth": 479.44713509,
		"ukwest": 479.44713509,
		"unitedstates": 0,
		"unitedstateseuap": 0,
		"westcentralus": 691.27477188,
		"westeurope": 0,
		"westindia": 0,
		"westus": 22.6796185,
		"westus2": 508.02345440000005,
		"westus2stage": 0,
		"westus3": 583.31978782,
		"westusstage": 0
	},
	"startDate": "2023-03-03T20:03:32.134897197Z",
	"userId": ""
}
