{
	"createdDate": "2023-06-09T20:38:40.530733086Z",
	"endDate": "2023-06-09T20:43:12.306169046Z",
	"id": "report",
	"intensities": {
		"asia": 0,
		"asiapacific": 0,
		"australia": 0,
		"australiacentral": 777.45732218,
		"australiacentral2": 777.45732218,
		"australiaeast": 777.45732218,
		"australiasoutheast": 772.46780611,
		"brazil": 0,
		"brazilsouth": 0,
		"brazilsoutheast": 0,
		"canada": 0,
		"canadacentral": 474.00402665,
		"canadaeast": 459.03547844,
		"centralindia": 0,
		"centralus": 593.29881996,
		"centraluseuap": 593.29881996,
		"centralusstage": 0,
		"eastasia": 0,
		"eastasiastage": 0,
		"eastus": 589.2164886300001,
		"eastus2": 589.2164886300001,
		"eastus2euap": 589.2164886300001,
		"eastus2stage": 0,
		"eastusstage": 0,
		"europe": 0,
		"france": 0,
		"francecentral": 0,
		"francesouth": 0,
		"germany": 0,
		"germanynorth": 0,
		"germanywestcentral": 0,
		"global": 0,
		"india": 0,
		"japan": 0,
		"japaneast": 0,
		"japanwest": 0,
		"jioindiacentral": 0,
		"jioindiawest": 0,
		"korea": 0,
		"koreacentral": 0,
		"koreasouth": 0,
		"northcentralus": 589.2164886300001,
		"northcentralusstage": 0,
		"northeurope": 513.92015521,
		"norway": 500,
		"norwayeast": 0,
		"norwaywest": 0,
		"southafrica": 0,
		"southafricanorth": 0,
		"southafricawest": 0,
		"southcentralus": 510.29141625,
		"southcentralusstage": 0,
		"southeastasia": 0,
		"southeastasiastage": 0,
		"southindia": 0,
		"swedencentral": 0,
		"switzerland": 0,
		"switzerlandnorth": 0,
		"switzerlandwest": 0,
		"uae": 0,
		"uaecentral": 0,
		"uaenorth": 0,
		"uk": 0,
		"uksouth": 431.81993624,
		"ukwest": 431.81993624,
		"unitedstates": 0,
		"unitedstateseuap": 0,
		"westcentralus": 618.69999268,
		"westeurope": 0,
		"westindia": 0,
		"westus": 172.81869297,
		"westus2": 308.89640397,
		"westus2stage": 0,
		"westus3": 478.08635798,
		"westusstage": 0
	},
	"startDate": "2023-06-09T20:38:12.306168972Z",
	"userId": ""
}
