{
	"createdDate": "2023-08-21T17:18:45.900709175Z",
	"endDate": "2023-08-21T17:23:18.947016072Z",
	"id": "report",
	"intensities": {
		"asia": 0,
		"asiapacific": 0,
		"australia": 0,
		"australiacentral": 821.0021897,
		"australiacentral2": 821.0021897,
		"australiaeast": 821.0021897,
		"australiasoutheast": 37.19457434,
		"brazil": 0,
		"brazilsouth": 0,
		"brazilsoutheast": 0,
		"canada": 0,
		"canadacentral": 482.16868931000005,
		"canadaeast": 471.7360648,
		"centralindia": 0,
		"centralus": 582.86619545,
		"centraluseuap": 582.86619545,
		"centralusstage": 0,
		"eastasia": 0,
		"eastasiastage": 0,
		"eastus": 606.90659106,
		"eastus2": 606.90659106,
		"eastus2euap": 606.90659106,
		"eastus2stage": 0,
		"eastusstage": 0,
		"europe": 0,
		"france": 0,
		"francecentral": 0,
		"francesouth": 0,
		"germany": 0,
		"germanynorth": 785.6219848400001,
		"germanywestcentral": 785.6219848400001,
		"global": 0,
		"india": 0,
		"japan": 0,
		"japaneast": 0,
		"japanwest": 0,
		"jioindiacentral": 0,
		"jioindiawest": 0,
		"korea": 0,
		"koreacentral": 0,
		"koreasouth": 0,
		"northcentralus": 606.90659106,
		"northcentralusstage": 0,
		"northeurope": 544.76443637,
		"norway": 438,
		"norwayeast": 0,
		"norwaywest": 0,
		"southafrica": 0,
		"southafricanorth": 0,
		"southafricawest": 0,
		"southcentralus": 519.81685602,
		"southcentralusstage": 0,
		"southeastasia": 0,
		"southeastasiastage": 0,
		"southindia": 0,
		"swedencentral": 0,
		"switzerland": 0,
		"switzerlandnorth": 0,
		"switzerlandwest": 0,
		"uae": 0,
		"uaecentral": 0,
		"uaenorth": 0,
		"uk": 0,
		"uksouth": 434.08789809,
		"ukwest": 434.08789809,
		"unitedstates": 0,
		"unitedstateseuap": 0,
		"westcentralus": 730.2837157,
		"westeurope": 0,
		"westindia": 0,
		"westus": 22.22602613,
		"westus2": 500.76597648,
		"westus2stage": 0,
		"westus3": 561.5473540600001,
		"westusstage": 0
	},
	"startDate": "2023-08-21T17:18:18.947015997Z",
	"userId": ""
}
