{
	"createdDate": "2023-02-11T02:00:54.431672234Z",
	"endDate": "2023-02-11T02:05:24.261869988Z",
	"id": "report",
	"intensities": {
		"asia": 0,
		"asiapacific": 0,
		"australia": 0,
		"australiacentral": 825.08452103,
		"australiacentral2": 825.08452103,
		"australiaeast": 825.08452103,
		"australiasoutheast": 0,
		"brazil": 0,
		"brazilsouth": 0,
		"brazilsoutheast": 0,
		"canada": 0,
		"canadacentral": 464.93217925000005,
		"canadaeast": 442.25256075,
		"centralindia": 0,
		"centralus": 635.029318,
		"centraluseuap": 635.029318,
		"centralusstage": 0,
		"eastasia": 0,
		"eastasiastage": 0,
		"eastus": 561.0937616900001,
		"eastus2": 561.0937616900001,
		"eastus2euap": 561.0937616900001,
		"eastus2stage": 0,
		"eastusstage": 0,
		"europe": 0,
		"france": 0,
		"francecentral": 370.58496629,
		"francesouth": 370.58496629,
		"germany": 0,
		"germanynorth": 796.50820172,
		"germanywestcentral": 796.50820172,
		"global": 0,
		"india": 0,
		"japan": 0,
		"japaneast": 0,
		"japanwest": 0,
		"jioindiacentral": 0,
		"jioindiawest": 0,
		"korea": 0,
		"koreacentral": 0,
		"koreasouth": 0,
		"northcentralus": 561.0937616900001,
		"northcentralusstage": 0,
		"northeurope": 0,
		"norway": 0,
		"norwayeast": 239.95036373000002,
		"norwaywest": 239.95036373000002,
		"southafrica": 0,
		"southafricanorth": 0,
		"southafricawest": 0,
		"southcentralus": 527.98151868,
		"southcentralusstage": 0,
		"southeastasia": 0,
		"southeastasiastage": 0,
		"southindia": 0,
		"swedencentral": 793.33305513,
		"switzerland": 0,
		"switzerlandnorth": 0,
		"switzerlandwest": 0,
		"uae": 0,
		"uaecentral": 0,
		"uaenorth": 0,
		"uk": 0,
		"uksouth": 409.14031774,
		"ukwest": 409.14031774,
		"unitedstates": 0,
		"unitedstateseuap": 0,
		"westcentralus": 693.54273373,
		"westeurope": 513.92015521,
		"westindia": 0,
		"westus": 454.49955474,
		"westus2": 507.56986203,
		"westus2stage": 0,
		"westus3": 592.39163522,
		"westusstage": 0
	},
	"startDate": "2023-02-11T02:00:24.261869913Z",
	"userId": ""
}
