{
	"createdDate": "2023-04-17T05:48:46.0336079Z",
	"endDate": "2023-04-17T05:53:18.889114102Z",
	"id": "report",
	"intensities": {
		"asia": 0,
		"asiapacific": 0,
		"australia": 0,
		"australiacentral": 774.7357679600001,
		"australiacentral2": 774.7357679600001,
		"australiaeast": 774.7357679600001,
		"australiasoutheast": 691.27477188,
		"brazil": 0,
		"brazilsouth": 0,
		"brazilsoutheast": 0,
		"canada": 0,
		"canadacentral": 0,
		"canadaeast": 443.15974549,
		"centralindia": 0,
		"centralus": 611.44251476,
		"centraluseuap": 611.44251476,
		"centralusstage": 0,
		"eastasia": 0,
		"eastasiastage": 0,
		"eastus": 538.41414319,
		"eastus2": 538.41414319,
		"eastus2euap": 538.41414319,
		"eastus2stage": 0,
		"eastusstage": 0,
		"europe": 0,
		"france": 0,
		"francecentral": 0,
		"francesouth": 0,
		"germany": 0,
		"germanynorth": 0,
		"germanywestcentral": 0,
		"global": 0,
		"india": 0,
		"japan": 0,
		"japaneast": 0,
		"japanwest": 0,
		"jioindiacentral": 0,
		"jioindiawest": 0,
		"korea": 0,
		"koreacentral": 0,
		"koreasouth": 0,
		"northcentralus": 10.88621688,
		"northcentralusstage": 0,
		"northeurope": 491.24053671,
		"norway": 438,
		"norwayeast": 0,
		"norwaywest": 0,
		"southafrica": 0,
		"southafricanorth": 0,
		"southafricawest": 0,
		"southcentralus": 528.43511105,
		"southcentralusstage": 0,
		"southeastasia": 0,
		"southeastasiastage": 0,
		"southindia": 0,
		"swedencentral": 0,
		"switzerland": 0,
		"switzerlandnorth": 0,
		"switzerlandwest": 0,
		"uae": 0,
		"uaecentral": 0,
		"uaenorth": 0,
		"uk": 0,
		"uksouth": 406.87235589,
		"ukwest": 406.87235589,
		"unitedstates": 0,
		"unitedstateseuap": 0,
		"westcentralus": 691.72836425,
		"westeurope": 0,
		"westindia": 0,
		"westus": 449.51003867000003,
		"westus2": 512.5593781,
		"westus2stage": 0,
		"westus3": 534.33181186,
		"westusstage": 0
	},
	"startDate": "2023-04-17T05:48:18.889113998Z",
	"userId": ""
}
