{
	"createdDate": "2022-12-19T07:25:53.256280495Z",
	"endDate": "2022-12-19T07:30:23.55301327Z",
	"id": "report",
	"intensities": {
		"asia": 0,
		"asiapacific": 0,
		"australia": 0,
		"australiacentral": 806.03364149,
		"australiacentral2": 806.03364149,
		"australiaeast": 806.03364149,
		"australiasoutheast": 698.9858421700001,
		"brazil": 0,
		"brazilsouth": 0,
		"brazilsoutheast": 0,
		"canada": 0,
		"canadacentral": 463.11780977,
		"canadaeast": 440.43819127,
		"centralindia": 0,
		"centralus": 616.43203083,
		"centraluseuap": 616.43203083,
		"centralusstage": 0,
		"eastasia": 0,
		"eastasiastage": 0,
		"eastus": 556.10424562,
		"eastus2": 556.10424562,
		"eastus2euap": 556.10424562,
		"eastus2stage": 0,
		"eastusstage": 0,
		"europe": 0,
		"france": 0,
		"francecentral": 0,
		"francesouth": 0,
		"germany": 0,
		"germanynorth": 0,
		"germanywestcentral": 0,
		"global": 0,
		"india": 0,
		"japan": 0,
		"japaneast": 0,
		"japanwest": 0,
		"jioindiacentral": 0,
		"jioindiawest": 0,
		"korea": 0,
		"koreacentral": 0,
		"koreasouth": 0,
		"northcentralus": 556.10424562,
		"northcentralusstage": 0,
		"northeurope": 275.33056859000004,
		"norway": 0,
		"norwayeast": 0,
		"norwaywest": 0,
		"southafrica": 0,
		"southafricanorth": 0,
		"southafricawest": 0,
		"southcentralus": 540.22851267,
		"southcentralusstage": 0,
		"southeastasia": 0,
		"southeastasiastage": 0,
		"southindia": 0,
		"swedencentral": 0,
		"switzerland": 0,
		"switzerlandnorth": 0,
		"switzerlandwest": 0,
		"uae": 0,
		"uaecentral": 0,
		"uaenorth": 0,
		"uk": 0,
		"uksouth": 436.80945231000004,
		"ukwest": 436.80945231000004,
		"unitedstates": 0,
		"unitedstateseuap": 0,
		"westcentralus": 661.79126783,
		"westeurope": 0,
		"westindia": 0,
		"westus": 433.63430572,
		"westus2": 499.85879174,
		"westus2stage": 0,
		"westus3": 536.14618134,
		"westusstage": 0
	},
	"startDate": "2022-12-19T07:25:23.553013195Z",
	"userId": ""
}
