{
	"createdDate": "2023-06-06T08:23:49.778758465Z",
	"endDate": "2023-06-06T08:28:05.489815659Z",
	"id": "report",
	"intensities": {
		"asia": 0,
		"asiapacific": 0,
		"australia": 0,
		"australiacentral": 736.18041651,
		"australiacentral2": 736.18041651,
		"australiaeast": 736.18041651,
		"australiasoutheast": 883.14434439,
		"brazil": 0,
		"brazilsouth": 0,
		"brazilsoutheast": 0,
		"canada": 0,
		"canadacentral": 442.25256075,
		"canadaeast": 429.55197439,
		"centralindia": 0,
		"centralus": 602.82425973,
		"centraluseuap": 602.82425973,
		"centralusstage": 0,
		"eastasia": 0,
		"eastasiastage": 0,
		"eastus": 526.6207415700001,
		"eastus2": 526.6207415700001,
		"eastus2euap": 526.6207415700001,
		"eastus2stage": 0,
		"eastusstage": 0,
		"europe": 0,
		"france": 0,
		"francecentral": 0,
		"francesouth": 0,
		"germany": 0,
		"germanynorth": 0,
		"germanywestcentral": 0,
		"global": 0,
		"india": 0,
		"japan": 0,
		"japaneast": 0,
		"japanwest": 0,
		"jioindiacentral": 0,
		"jioindiawest": 0,
		"korea": 0,
		"koreacentral": 0,
		"koreasouth": 0,
		"northcentralus": 526.6207415700001,
		"northcentralusstage": 0,
		"northeurope": 568.35123961,
		"norway": 1153,
		"norwayeast": 0,
		"norwaywest": 0,
		"southafrica": 0,
		"southafricanorth": 0,
		"southafricawest": 0,
		"southcentralus": 525.71355683,
		"southcentralusstage": 0,
		"southeastasia": 0,
		"southeastasiastage": 0,
		"southindia": 0,
		"swedencentral": 0,
		"switzerland": 0,
		"switzerlandnorth": 0,
		"switzerlandwest": 0,
		"uae": 0,
		"uaecentral": 0,
		"uaenorth": 0,
		"uk": 0,
		"uksouth": 386.91429161,
		"ukwest": 386.91429161,
		"unitedstates": 0,
		"unitedstateseuap": 0,
		"westcentralus": 693.54273373,
		"westeurope": 0,
		"westindia": 0,
		"westus": 411.40827959,
		"westus2": 411.40827959,
		"westus2stage": 0,
		"westus3": 515.28093232,
		"westusstage": 0
	},
	"startDate": "2023-06-06T08:23:05.489815596Z",
	"userId": ""
}
