{
	"createdDate": "2023-02-26T10:00:50.829737717Z",
	"endDate": "2023-02-26T10:05:20.261104569Z",
	"id": "report",
	"intensities": {
		"asia": 0,
		"asiapacific": 0,
		"australia": 0,
		"australiacentral": 759.7672197500001,
		"australiacentral2": 759.7672197500001,
		"australiaeast": 759.7672197500001,
		"australiasoutheast": 688.09962529,
		"brazil": 0,
		"brazilsouth": 0,
		"brazilsoutheast": 0,
		"canada": 0,
		"canadacentral": 450.87081578,
		"canadaeast": 434.54149046,
		"centralindia": 0,
		"centralus": 663.15204494,
		"centraluseuap": 663.15204494,
		"centralusstage": 0,
		"eastasia": 0,
		"eastasiastage": 0,
		"eastus": 559.73298458,
		"eastus2": 559.73298458,
		"eastus2euap": 559.73298458,
		"eastus2stage": 0,
		"eastusstage": 0,
		"europe": 0,
		"france": 0,
		"francecentral": 0,
		"francesouth": 0,
		"germany": 0,
		"germanynorth": 0,
		"germanywestcentral": 0,
		"global": 0,
		"india": 0,
		"japan": 0,
		"japaneast": 0,
		"japanwest": 0,
		"jioindiacentral": 0,
		"jioindiawest": 0,
		"korea": 0,
		"koreacentral": 0,
		"koreasouth": 0,
		"northcentralus": 559.73298458,
		"northcentralusstage": 0,
		"northeurope": 0,
		"norway": 0,
		"norwayeast": 0,
		"norwaywest": 0,
		"southafrica": 0,
		"southafricanorth": 0,
		"southafricawest": 0,
		"southcentralus": 580.5982336000001,
		"southcentralusstage": 0,
		"southeastasia": 0,
		"southeastasiastage": 0,
		"southindia": 0,
		"swedencentral": 0,
		"switzerland": 0,
		"switzerlandnorth": 0,
		"switzerlandwest": 0,
		"uae": 0,
		"uaecentral": 0,
		"uaenorth": 0,
		"uk": 0,
		"uksouth": 422.74808884000004,
		"ukwest": 422.74808884000004,
		"unitedstates": 0,
		"unitedstateseuap": 0,
		"westcentralus": 715.31516749,
		"westeurope": 0,
		"westindia": 0,
		"westus": 449.0564463,
		"westus2": 510.74500862,
		"westus2stage": 0,
		"westus3": 599.64911314,
		"westusstage": 0
	},
	"startDate": "2023-02-26T10:00:20.261104493Z",
	"userId": ""
}
