{
	"createdDate": "2023-01-02T15:53:48.962129374Z",
	"endDate": "2023-01-02T15:58:17.840340857Z",
	"id": "report",
	"intensities": {
		"asia": 0,
		"asiapacific": 0,
		"australia": 0,
		"australiacentral": 875.88686647,
		"australiacentral2": 875.88686647,
		"australiaeast": 875.88686647,
		"australiasoutheast": 757.4992579000001,
		"brazil": 0,
		"brazilsouth": 0,
		"brazilsoutheast": 0,
		"canada": 0,
		"canadacentral": 476.72558087,
		"canadaeast": 459.03547844,
		"centralindia": 0,
		"centralus": 620.96795453,
		"centraluseuap": 620.96795453,
		"centralusstage": 0,
		"eastasia": 0,
		"eastasiastage": 0,
		"eastus": 558.82579984,
		"eastus2": 558.82579984,
		"eastus2euap": 558.82579984,
		"eastus2stage": 0,
		"eastusstage": 0,
		"europe": 0,
		"france": 0,
		"francecentral": 0,
		"francesouth": 0,
		"germany": 0,
		"germanynorth": 0,
		"germanywestcentral": 0,
		"global": 0,
		"india": 0,
		"japan": 0,
		"japaneast": 0,
		"japanwest": 0,
		"jioindiacentral": 0,
		"jioindiawest": 0,
		"korea": 0,
		"koreacentral": 0,
		"koreasouth": 0,
		"northcentralus": 558.82579984,
		"northcentralusstage": 0,
		"northeurope": 515.28093232,
		"norway": 0,
		"norwayeast": 0,
		"norwaywest": 0,
		"southafrica": 0,
		"southafricanorth": 0,
		"southafricawest": 0,
		"southcentralus": 570.61920146,
		"southcentralusstage": 0,
		"southeastasia": 0,
		"southeastasiastage": 0,
		"southindia": 0,
		"swedencentral": 0,
		"switzerland": 0,
		"switzerlandnorth": 0,
		"switzerlandwest": 0,
		"uae": 0,
		"uaecentral": 0,
		"uaenorth": 0,
		"uk": 0,
		"uksouth": 465.38577162,
		"ukwest": 465.38577162,
		"unitedstates": 0,
		"unitedstateseuap": 0,
		"westcentralus": 707.6040972000001,
		"westeurope": 0,
		"westindia": 0,
		"westus": 464.02499451,
		"westus2": 591.03085811,
		"westus2stage": 0,
		"westus3": 570.61920146,
		"westusstage": 0
	},
	"startDate": "2023-01-02T15:53:17.840340767Z",
	"userId": ""
}
