{
	"createdDate": "2023-06-27T03:20:50.156242227Z",
	"endDate": "2023-06-27T03:25:15.138400988Z",
	"id": "report",
	"intensities": {
		"asia": 0,
		"asiapacific": 0,
		"australia": 0,
		"australiacentral": 770.1998442600001,
		"australiacentral2": 770.1998442600001,
		"australiaeast": 770.1998442600001,
		"australiasoutheast": 606.90659106,
		"brazil": 0,
		"brazilsouth": 0,
		"brazilsoutheast": 0,
		"canada": 0,
		"canadacentral": 473.09684191,
		"canadaeast": 454.49955474,
		"centralindia": 0,
		"centralus": 0,
		"centraluseuap": 633.66854089,
		"centralusstage": 0,
		"eastasia": 0,
		"eastasiastage": 0,
		"eastus": 569.7120167200001,
		"eastus2": 569.7120167200001,
		"eastus2euap": 569.7120167200001,
		"eastus2stage": 0,
		"eastusstage": 0,
		"europe": 0,
		"france": 0,
		"francecentral": 0,
		"francesouth": 0,
		"germany": 0,
		"germanynorth": 0,
		"germanywestcentral": 0,
		"global": 0,
		"india": 0,
		"japan": 0,
		"japaneast": 0,
		"japanwest": 0,
		"jioindiacentral": 0,
		"jioindiawest": 0,
		"korea": 0,
		"koreacentral": 0,
		"koreasouth": 0,
		"northcentralus": 569.7120167200001,
		"northcentralusstage": 0,
		"northeurope": 0,
		"norway": 1132,
		"norwayeast": 0,
		"norwaywest": 0,
		"southafrica": 0,
		"southafricanorth": 0,
		"southafricawest": 0,
		"southcentralus": 509.38423151,
		"southcentralusstage": 0,
		"southeastasia": 0,
		"southeastasiastage": 0,
		"southindia": 0,
		"swedencentral": 0,
		"switzerland": 0,
		"switzerlandnorth": 0,
		"switzerlandwest": 0,
		"uae": 0,
		"uaecentral": 0,
		"uaenorth": 0,
		"uk": 0,
		"uksouth": 386.91429161,
		"ukwest": 386.91429161,
		"unitedstates": 0,
		"unitedstateseuap": 0,
		"westcentralus": 710.32565142,
		"westeurope": 0,
		"westindia": 0,
		"westus": 447.24207682,
		"westus2": 504.84830781000005,
		"westus2stage": 0,
		"westus3": 515.73452469,
		"westusstage": 0
	},
	"startDate": "2023-06-27T03:20:15.138400912Z",
	"userId": ""
}
