{
	"createdDate": "2023-08-28T18:38:46.671220247Z",
	"endDate": "2023-08-28T18:43:16.398596674Z",
	"id": "report",
	"intensities": {
		"asia": 0,
		"asiapacific": 0,
		"australia": 0,
		"australiacentral": 838.69229213,
		"australiacentral2": 838.69229213,
		"australiaeast": 838.69229213,
		"australiasoutheast": 739.3555631,
		"brazil": 0,
		"brazilsouth": 0,
		"brazilsoutheast": 0,
		"canada": 0,
		"canadacentral": 482.16868931000005,
		"canadaeast": 475.36480376000003,
		"centralindia": 0,
		"centralus": 587.4021191500001,
		"centraluseuap": 587.4021191500001,
		"centralusstage": 0,
		"eastasia": 0,
		"eastasiastage": 0,
		"eastus": 569.25842435,
		"eastus2": 569.25842435,
		"eastus2euap": 569.25842435,
		"eastus2stage": 0,
		"eastusstage": 0,
		"europe": 0,
		"france": 0,
		"francecentral": 0,
		"francesouth": 0,
		"germany": 0,
		"germanynorth": 0,
		"germanywestcentral": 0,
		"global": 0,
		"india": 0,
		"japan": 0,
		"japaneast": 0,
		"japanwest": 0,
		"jioindiacentral": 0,
		"jioindiawest": 0,
		"korea": 0,
		"koreacentral": 0,
		"koreasouth": 0,
		"northcentralus": 569.25842435,
		"northcentralusstage": 0,
		"northeurope": 551.11472955,
		"norway": 464,
		"norwayeast": 0,
		"norwaywest": 0,
		"southafrica": 0,
		"southafricanorth": 0,
		"southafricawest": 0,
		"southcentralus": 524.35277972,
		"southcentralusstage": 0,
		"southeastasia": 0,
		"southeastasiastage": 0,
		"southindia": 0,
		"swedencentral": 0,
		"switzerland": 0,
		"switzerlandnorth": 0,
		"switzerlandwest": 0,
		"uae": 0,
		"uaecentral": 0,
		"uaenorth": 0,
		"uk": 0,
		"uksouth": 420.48012699000003,
		"ukwest": 420.48012699000003,
		"unitedstates": 0,
		"unitedstateseuap": 0,
		"westcentralus": 662.2448602,
		"westeurope": 0,
		"westindia": 0,
		"westus": 446.33489208000003,
		"westus2": 487.15820538,
		"westus2stage": 0,
		"westus3": 528.8887034200001,
		"westusstage": 0
	},
	"startDate": "2023-08-28T18:38:16.3985966Z",
	"userId": ""
}
