{
	"createdDate": "2023-05-25T22:53:46.497227815Z",
	"endDate": "2023-05-25T22:58:18.834482528Z",
	"id": "report",
	"intensities": {
		"asia": 0,
		"asiapacific": 0,
		"australia": 0,
		"australiacentral": 777.0037298100001,
		"australiacentral2": 777.0037298100001,
		"australiaeast": 777.0037298100001,
		"australiasoutheast": 472.18965717000003,
		"brazil": 0,
		"brazilsouth": 0,
		"brazilsoutheast": 0,
		"canada": 0,
		"canadacentral": 471.28247243000004,
		"canadaeast": 453.59237,
		"centralindia": 0,
		"centralus": 675.3990389300001,
		"centraluseuap": 675.3990389300001,
		"centralusstage": 0,
		"eastasia": 0,
		"eastasiastage": 0,
		"eastus": 597.8347436600001,
		"eastus2": 597.8347436600001,
		"eastus2euap": 597.8347436600001,
		"eastus2stage": 0,
		"eastusstage": 0,
		"europe": 0,
		"france": 0,
		"francecentral": 0,
		"francesouth": 0,
		"germany": 0,
		"germanynorth": 0,
		"germanywestcentral": 0,
		"global": 0,
		"india": 0,
		"japan": 0,
		"japaneast": 0,
		"japanwest": 0,
		"jioindiacentral": 0,
		"jioindiawest": 0,
		"korea": 0,
		"koreacentral": 0,
		"koreasouth": 0,
		"northcentralus": 168.28276927000002,
		"northcentralusstage": 0,
		"northeurope": 541.13569741,
		"norway": 438,
		"norwayeast": 0,
		"norwaywest": 0,
		"southafrica": 0,
		"southafricanorth": 0,
		"southafricawest": 0,
		"southcentralus": 498.951607,
		"southcentralusstage": 0,
		"southeastasia": 0,
		"southeastasiastage": 0,
		"southindia": 0,
		"swedencentral": 0,
		"switzerland": 0,
		"switzerlandnorth": 0,
		"switzerlandwest": 0,
		"uae": 0,
		"uaecentral": 0,
		"uaenorth": 0,
		"uk": 0,
		"uksouth": 421.38731173,
		"ukwest": 421.38731173,
		"unitedstates": 0,
		"unitedstateseuap": 0,
		"westcentralus": 700.80021165,
		"westeurope": 0,
		"westindia": 0,
		"westus": 23.133210870000003,
		"westus2": 519.81685602,
		"westus2stage": 0,
		"westus3": 546.1252134800001,
		"westusstage": 0
	},
	"startDate": "2023-05-25T22:53:18.834482454Z",
	"userId": ""
}
