{
	"createdDate": "2023-04-17T23:03:47.545940589Z",
	"endDate": "2023-04-17T23:08:19.034649684Z",
	"id": "report",
	"intensities": {
		"asia": 0,
		"asiapacific": 0,
		"australia": 0,
		"australiacentral": 799.68334831,
		"australiacentral2": 799.68334831,
		"australiaeast": 799.68334831,
		"australiasoutheast": 836.8779226500001,
		"brazil": 0,
		"brazilsouth": 0,
		"brazilsoutheast": 0,
		"canada": 0,
		"canadacentral": 511.19860099,
		"canadaeast": 484.43665116,
		"centralindia": 0,
		"centralus": 665.42000679,
		"centraluseuap": 665.42000679,
		"centralusstage": 0,
		"eastasia": 0,
		"eastasiastage": 0,
		"eastus": 556.55783799,
		"eastus2": 556.55783799,
		"eastus2euap": 556.55783799,
		"eastus2stage": 0,
		"eastusstage": 0,
		"europe": 0,
		"france": 0,
		"francecentral": 0,
		"francesouth": 0,
		"germany": 0,
		"germanynorth": 805.58004912,
		"germanywestcentral": 805.58004912,
		"global": 0,
		"india": 0,
		"japan": 0,
		"japaneast": 0,
		"japanwest": 0,
		"jioindiacentral": 0,
		"jioindiawest": 0,
		"korea": 0,
		"koreacentral": 0,
		"koreasouth": 0,
		"northcentralus": 556.55783799,
		"northcentralusstage": 0,
		"northeurope": 197.76627332,
		"norway": 832,
		"norwayeast": 377.38885184000003,
		"norwaywest": 377.38885184000003,
		"southafrica": 0,
		"southafricanorth": 0,
		"southafricawest": 0,
		"southcentralus": 533.4246271200001,
		"southcentralusstage": 0,
		"southeastasia": 0,
		"southeastasiastage": 0,
		"southindia": 0,
		"swedencentral": 0,
		"switzerland": 0,
		"switzerlandnorth": 0,
		"switzerlandwest": 0,
		"uae": 0,
		"uaecentral": 0,
		"uaenorth": 0,
		"uk": 0,
		"uksouth": 433.63430572,
		"ukwest": 433.63430572,
		"unitedstates": 0,
		"unitedstateseuap": 0,
		"westcentralus": 653.62660517,
		"westeurope": 0,
		"westindia": 0,
		"westus": 23.133210870000003,
		"westus2": 469.01451058,
		"westus2stage": 0,
		"westus3": 545.21802874,
		"westusstage": 0
	},
	"startDate": "2023-04-17T23:03:19.034649612Z",
	"userId": ""
}
