{
	"createdDate": "2023-06-21T03:43:45.080755952Z",
	"endDate": "2023-06-21T03:48:19.198886148Z",
	"id": "report",
	"intensities": {
		"asia": 0,
		"asiapacific": 0,
		"australia": 0,
		"australiacentral": 768.3854747800001,
		"australiacentral2": 768.3854747800001,
		"australiaeast": 768.3854747800001,
		"australiasoutheast": 633.21494852,
		"brazil": 0,
		"brazilsouth": 0,
		"brazilsoutheast": 0,
		"canada": 0,
		"canadacentral": 470.37528769000005,
		"canadaeast": 450.41722341,
		"centralindia": 0,
		"centralus": 675.8526313,
		"centraluseuap": 675.8526313,
		"centralusstage": 0,
		"eastasia": 0,
		"eastasiastage": 0,
		"eastus": 596.47396655,
		"eastus2": 596.47396655,
		"eastus2euap": 596.47396655,
		"eastus2stage": 0,
		"eastusstage": 0,
		"europe": 0,
		"france": 0,
		"francecentral": 0,
		"francesouth": 0,
		"germany": 0,
		"germanynorth": 0,
		"germanywestcentral": 0,
		"global": 0,
		"india": 0,
		"japan": 0,
		"japaneast": 0,
		"japanwest": 0,
		"jioindiacentral": 0,
		"jioindiawest": 0,
		"korea": 0,
		"koreacentral": 0,
		"koreasouth": 0,
		"northcentralus": 596.47396655,
		"northcentralusstage": 0,
		"northeurope": 487.61179775000005,
		"norway": 830,
		"norwayeast": 0,
		"norwaywest": 0,
		"southafrica": 0,
		"southafricanorth": 0,
		"southafricawest": 0,
		"southcentralus": 503.4875307,
		"southcentralusstage": 0,
		"southeastasia": 0,
		"southeastasiastage": 0,
		"southindia": 0,
		"swedencentral": 0,
		"switzerland": 0,
		"switzerlandnorth": 0,
		"switzerlandwest": 0,
		"uae": 0,
		"uaecentral": 0,
		"uaenorth": 0,
		"uk": 0,
		"uksouth": 386.91429161,
		"ukwest": 386.91429161,
		"unitedstates": 0,
		"unitedstateseuap": 0,
		"westcentralus": 681.7493321100001,
		"westeurope": 0,
		"westindia": 0,
		"westus": 424.10886595,
		"westus2": 423.20168121,
		"westus2stage": 0,
		"westus3": 497.59082989,
		"westusstage": 0
	},
	"startDate": "2023-06-21T03:43:19.198886061Z",
	"userId": ""
}
