{
	"createdDate": "2022-12-28T10:13:53.013524275Z",
	"endDate": "2022-12-28T10:18:19.222970761Z",
	"id": "report",
	"intensities": {
		"asia": 0,
		"asiapacific": 0,
		"australia": 0,
		"australiacentral": 788.79713143,
		"australiacentral2": 788.79713143,
		"australiaeast": 788.79713143,
		"australiasoutheast": 745.70585628,
		"brazil": 0,
		"brazilsouth": 0,
		"brazilsoutheast": 0,
		"canada": 0,
		"canadacentral": 0,
		"canadaeast": 421.84090410000005,
		"centralindia": 0,
		"centralus": 532.97103475,
		"centraluseuap": 532.97103475,
		"centralusstage": 0,
		"eastasia": 0,
		"eastasiastage": 0,
		"eastus": 577.42308701,
		"eastus2": 577.42308701,
		"eastus2euap": 577.42308701,
		"eastus2stage": 0,
		"eastusstage": 0,
		"europe": 0,
		"france": 0,
		"francecentral": 0,
		"francesouth": 0,
		"germany": 0,
		"germanynorth": 0,
		"germanywestcentral": 0,
		"global": 0,
		"india": 0,
		"japan": 0,
		"japaneast": 0,
		"japanwest": 0,
		"jioindiacentral": 0,
		"jioindiawest": 0,
		"korea": 0,
		"koreacentral": 0,
		"koreasouth": 0,
		"northcentralus": 577.42308701,
		"northcentralusstage": 0,
		"northeurope": 508.47704677,
		"norway": 0,
		"norwayeast": 0,
		"norwaywest": 0,
		"southafrica": 0,
		"southafricanorth": 0,
		"southafricawest": 0,
		"southcentralus": 529.34229579,
		"southcentralusstage": 0,
		"southeastasia": 0,
		"southeastasiastage": 0,
		"southindia": 0,
		"swedencentral": 0,
		"switzerland": 0,
		"switzerlandnorth": 0,
		"switzerlandwest": 0,
		"uae": 0,
		"uaecentral": 0,
		"uaenorth": 0,
		"uk": 0,
		"uksouth": 439.07741416000005,
		"ukwest": 439.07741416000005,
		"unitedstates": 0,
		"unitedstateseuap": 0,
		"westcentralus": 651.81223569,
		"westeurope": 0,
		"westindia": 0,
		"westus": 424.56245832,
		"westus2": 482.62228168,
		"westus2stage": 0,
		"westus3": 532.97103475,
		"westusstage": 0
	},
	"startDate": "2022-12-28T10:13:19.222970685Z",
	"userId": ""
}
