{
	"createdDate": "2023-06-20T03:18:44.923144536Z",
	"endDate": "2023-06-20T03:23:18.893508548Z",
	"id": "report",
	"intensities": {
		"asia": 0,
		"asiapacific": 0,
		"australia": 0,
		"australiacentral": 772.46780611,
		"australiacentral2": 772.46780611,
		"australiaeast": 772.46780611,
		"australiasoutheast": 626.86465534,
		"brazil": 0,
		"brazilsouth": 0,
		"brazilsoutheast": 0,
		"canada": 0,
		"canadacentral": 470.82888006,
		"canadaeast": 451.32440815,
		"centralindia": 0,
		"centralus": 669.95593049,
		"centraluseuap": 669.95593049,
		"centralusstage": 0,
		"eastasia": 0,
		"eastasiastage": 0,
		"eastus": 597.38115129,
		"eastus2": 597.38115129,
		"eastus2euap": 597.38115129,
		"eastus2stage": 0,
		"eastusstage": 0,
		"europe": 0,
		"france": 0,
		"francecentral": 0,
		"francesouth": 0,
		"germany": 0,
		"germanynorth": 799.68334831,
		"germanywestcentral": 799.68334831,
		"global": 0,
		"india": 0,
		"japan": 0,
		"japaneast": 0,
		"japanwest": 0,
		"jioindiacentral": 0,
		"jioindiawest": 0,
		"korea": 0,
		"koreacentral": 0,
		"koreasouth": 0,
		"northcentralus": 597.38115129,
		"northcentralusstage": 0,
		"northeurope": 490.33335197,
		"norway": 657,
		"norwayeast": 0,
		"norwaywest": 0,
		"southafrica": 0,
		"southafricanorth": 0,
		"southafricawest": 0,
		"southcentralus": 508.47704677,
		"southcentralusstage": 0,
		"southeastasia": 0,
		"southeastasiastage": 0,
		"southindia": 0,
		"swedencentral": 0,
		"switzerland": 0,
		"switzerlandnorth": 0,
		"switzerlandwest": 0,
		"uae": 0,
		"uaecentral": 0,
		"uaenorth": 0,
		"uk": 0,
		"uksouth": 386.91429161,
		"ukwest": 386.91429161,
		"unitedstates": 0,
		"unitedstateseuap": 0,
		"westcentralus": 663.15204494,
		"westeurope": 0,
		"westindia": 0,
		"westus": 431.81993624,
		"westus2": 488.51898249000004,
		"westus2stage": 0,
		"westus3": 524.35277972,
		"westusstage": 0
	},
	"startDate": "2023-06-20T03:18:18.893508384Z",
	"userId": ""
}
