{
	"createdDate": "2022-10-25T02:03:47.275908166Z",
	"endDate": "2022-10-25T02:08:19.317977288Z",
	"id": "report",
	"intensities": {
		"asia": 0,
		"asiapacific": 0,
		"australia": 0,
		"australiacentral": 854.5680250800001,
		"australiacentral2": 854.5680250800001,
		"australiaeast": 854.5680250800001,
		"australiasoutheast": 808.75519571,
		"brazil": 0,
		"brazilsouth": 0,
		"brazilsoutheast": 0,
		"canada": 0,
		"canadacentral": 485.3438359,
		"canadaeast": 463.57140214000003,
		"centralindia": 0,
		"centralus": 702.16098876,
		"centraluseuap": 702.16098876,
		"centralusstage": 0,
		"eastasia": 0,
		"eastasiastage": 0,
		"eastus": 561.0937616900001,
		"eastus2": 561.0937616900001,
		"eastus2euap": 561.0937616900001,
		"eastus2stage": 0,
		"eastusstage": 0,
		"europe": 0,
		"france": 0,
		"francecentral": 0,
		"francesouth": 0,
		"germany": 0,
		"germanynorth": 0,
		"germanywestcentral": 0,
		"global": 0,
		"india": 0,
		"japan": 0,
		"japaneast": 0,
		"japanwest": 0,
		"jioindiacentral": 0,
		"jioindiawest": 0,
		"korea": 0,
		"koreacentral": 0,
		"koreasouth": 0,
		"northcentralus": 561.0937616900001,
		"northcentralusstage": 0,
		"northeurope": 529.79588816,
		"norway": 0,
		"norwayeast": 0,
		"norwaywest": 0,
		"southafrica": 0,
		"southafricanorth": 0,
		"southafricawest": 0,
		"southcentralus": 528.43511105,
		"southcentralusstage": 0,
		"southeastasia": 0,
		"southeastasiastage": 0,
		"southindia": 0,
		"swedencentral": 0,
		"switzerland": 0,
		"switzerlandnorth": 0,
		"switzerlandwest": 0,
		"uae": 0,
		"uaecentral": 0,
		"uaenorth": 0,
		"uk": 0,
		"uksouth": 386.91429161,
		"ukwest": 386.91429161,
		"unitedstates": 0,
		"unitedstateseuap": 0,
		"westcentralus": 738.90197073,
		"westeurope": 0,
		"westindia": 0,
		"westus": 438.62382179,
		"westus2": 486.25102064,
		"westus2stage": 0,
		"westus3": 531.15666527,
		"westusstage": 0
	},
	"startDate": "2022-10-25T02:03:19.317977215Z",
	"userId": ""
}
