{
	"createdDate": "2023-05-05T19:48:46.071506449Z",
	"endDate": "2023-05-05T19:53:19.089761093Z",
	"id": "report",
	"intensities": {
		"asia": 0,
		"asiapacific": 0,
		"australia": 0,
		"australiacentral": 799.68334831,
		"australiacentral2": 799.68334831,
		"australiaeast": 799.68334831,
		"australiasoutheast": 647.7299043600001,
		"brazil": 0,
		"brazilsouth": 0,
		"brazilsoutheast": 0,
		"canada": 0,
		"canadacentral": 445.88129971,
		"canadaeast": 432.72712098,
		"centralindia": 0,
		"centralus": 645.4619425100001,
		"centraluseuap": 645.4619425100001,
		"centralusstage": 0,
		"eastasia": 0,
		"eastasiastage": 0,
		"eastus": 596.47396655,
		"eastus2": 596.47396655,
		"eastus2euap": 596.47396655,
		"eastus2stage": 0,
		"eastusstage": 0,
		"europe": 0,
		"france": 0,
		"francecentral": 0,
		"francesouth": 0,
		"germany": 0,
		"germanynorth": 0,
		"germanywestcentral": 0,
		"global": 0,
		"india": 0,
		"japan": 0,
		"japaneast": 0,
		"japanwest": 0,
		"jioindiacentral": 0,
		"jioindiawest": 0,
		"korea": 0,
		"koreacentral": 0,
		"koreasouth": 0,
		"northcentralus": 596.47396655,
		"northcentralusstage": 0,
		"northeurope": 531.15666527,
		"norway": 590,
		"norwayeast": 0,
		"norwaywest": 0,
		"southafrica": 0,
		"southafricanorth": 0,
		"southafricawest": 0,
		"southcentralus": 525.25996446,
		"southcentralusstage": 0,
		"southeastasia": 0,
		"southeastasiastage": 0,
		"southindia": 0,
		"swedencentral": 0,
		"switzerland": 0,
		"switzerlandnorth": 0,
		"switzerlandwest": 0,
		"uae": 0,
		"uaecentral": 0,
		"uaenorth": 0,
		"uk": 0,
		"uksouth": 463.11780977,
		"ukwest": 463.11780977,
		"unitedstates": 0,
		"unitedstateseuap": 0,
		"westcentralus": 754.32411131,
		"westeurope": 0,
		"westindia": 0,
		"westus": 24.94758035,
		"westus2": 540.68210504,
		"westus2stage": 0,
		"westus3": 579.69104886,
		"westusstage": 0
	},
	"startDate": "2023-05-05T19:48:19.089761019Z",
	"userId": ""
}
