{
	"createdDate": "2022-12-18T19:10:54.975597556Z",
	"endDate": "2022-12-18T19:15:24.966813851Z",
	"id": "report",
	"intensities": {
		"asia": 0,
		"asiapacific": 0,
		"australia": 0,
		"australiacentral": 827.80607525,
		"australiacentral2": 827.80607525,
		"australiaeast": 827.80607525,
		"australiasoutheast": 859.10394878,
		"brazil": 0,
		"brazilsouth": 0,
		"brazilsoutheast": 0,
		"canada": 0,
		"canadacentral": 464.47858688,
		"canadaeast": 445.42770734000004,
		"centralindia": 0,
		"centralus": 620.51436216,
		"centraluseuap": 620.51436216,
		"centralusstage": 0,
		"eastasia": 0,
		"eastasiastage": 0,
		"eastus": 572.43357094,
		"eastus2": 572.43357094,
		"eastus2euap": 572.43357094,
		"eastus2stage": 0,
		"eastusstage": 0,
		"europe": 0,
		"france": 0,
		"francecentral": 0,
		"francesouth": 0,
		"germany": 0,
		"germanynorth": 0,
		"germanywestcentral": 0,
		"global": 0,
		"india": 0,
		"japan": 0,
		"japaneast": 0,
		"japanwest": 0,
		"jioindiacentral": 0,
		"jioindiawest": 0,
		"korea": 0,
		"koreacentral": 0,
		"koreasouth": 0,
		"northcentralus": 572.43357094,
		"northcentralusstage": 0,
		"northeurope": 513.01297047,
		"norway": 0,
		"norwayeast": 0,
		"norwaywest": 0,
		"southafrica": 0,
		"southafricanorth": 0,
		"southafricawest": 0,
		"southcentralus": 553.3826914,
		"southcentralusstage": 0,
		"southeastasia": 0,
		"southeastasiastage": 0,
		"southindia": 0,
		"swedencentral": 0,
		"switzerland": 0,
		"switzerlandnorth": 0,
		"switzerlandwest": 0,
		"uae": 0,
		"uaecentral": 0,
		"uaenorth": 0,
		"uk": 0,
		"uksouth": 434.99508283,
		"ukwest": 434.99508283,
		"unitedstates": 0,
		"unitedstateseuap": 0,
		"westcentralus": 722.57264541,
		"westeurope": 0,
		"westindia": 0,
		"westus": 472.18965717000003,
		"westus2": 580.14464123,
		"westus2stage": 0,
		"westus3": 624.14310112,
		"westusstage": 0
	},
	"startDate": "2022-12-18T19:10:24.966813771Z",
	"userId": ""
}
