{
	"createdDate": "2023-04-06T22:28:46.896321111Z",
	"endDate": "2023-04-06T22:33:19.199164764Z",
	"id": "report",
	"intensities": {
		"asia": 0,
		"asiapacific": 0,
		"australia": 0,
		"australiacentral": 812.83752704,
		"australiacentral2": 812.83752704,
		"australiaeast": 812.83752704,
		"australiasoutheast": 814.19830415,
		"brazil": 0,
		"brazilsouth": 0,
		"brazilsoutheast": 0,
		"canada": 0,
		"canadacentral": 0,
		"canadaeast": 449.96363104,
		"centralindia": 0,
		"centralus": 643.64757303,
		"centraluseuap": 643.64757303,
		"centralusstage": 0,
		"eastasia": 0,
		"eastasiastage": 0,
		"eastus": 546.1252134800001,
		"eastus2": 546.1252134800001,
		"eastus2euap": 546.1252134800001,
		"eastus2stage": 0,
		"eastusstage": 0,
		"europe": 0,
		"france": 0,
		"francecentral": 0,
		"francesouth": 0,
		"germany": 0,
		"germanynorth": 0,
		"germanywestcentral": 0,
		"global": 0,
		"india": 0,
		"japan": 0,
		"japaneast": 0,
		"japanwest": 0,
		"jioindiacentral": 0,
		"jioindiawest": 0,
		"korea": 0,
		"koreacentral": 0,
		"koreasouth": 0,
		"northcentralus": 546.1252134800001,
		"northcentralusstage": 0,
		"northeurope": 551.56832192,
		"norway": 438,
		"norwayeast": 0,
		"norwaywest": 0,
		"southafrica": 0,
		"southafricanorth": 0,
		"southafricawest": 0,
		"southcentralus": 542.0428821500001,
		"southcentralusstage": 0,
		"southeastasia": 0,
		"southeastasiastage": 0,
		"southindia": 0,
		"swedencentral": 0,
		"switzerland": 0,
		"switzerlandnorth": 0,
		"switzerlandwest": 0,
		"uae": 0,
		"uaecentral": 0,
		"uaenorth": 0,
		"uk": 0,
		"uksouth": 409.59391011,
		"ukwest": 409.59391011,
		"unitedstates": 0,
		"unitedstateseuap": 0,
		"westcentralus": 650.90505095,
		"westeurope": 0,
		"westindia": 0,
		"westus": 29.02991168,
		"westus2": 489.8797596,
		"westus2stage": 0,
		"westus3": 575.15512516,
		"westusstage": 0
	},
	"startDate": "2023-04-06T22:28:19.19916468Z",
	"userId": ""
}
