{
	"createdDate": "2023-06-27T17:53:47.245157833Z",
	"endDate": "2023-06-27T17:58:18.89944069Z",
	"id": "report",
	"intensities": {
		"asia": 0,
		"asiapacific": 0,
		"australia": 0,
		"australiacentral": 787.4363543200001,
		"australiacentral2": 787.4363543200001,
		"australiaeast": 787.4363543200001,
		"australiasoutheast": 705.7897277200001,
		"brazil": 0,
		"brazilsouth": 0,
		"brazilsoutheast": 0,
		"canada": 0,
		"canadacentral": 480.35431983,
		"canadaeast": 467.65373347,
		"centralindia": 0,
		"centralus": 583.77338019,
		"centraluseuap": 583.77338019,
		"centralusstage": 0,
		"eastasia": 0,
		"eastasiastage": 0,
		"eastus": 572.43357094,
		"eastus2": 572.43357094,
		"eastus2euap": 572.43357094,
		"eastus2stage": 0,
		"eastusstage": 0,
		"europe": 0,
		"france": 0,
		"francecentral": 0,
		"francesouth": 0,
		"germany": 0,
		"germanynorth": 0,
		"germanywestcentral": 0,
		"global": 0,
		"india": 0,
		"japan": 0,
		"japaneast": 0,
		"japanwest": 0,
		"jioindiacentral": 0,
		"jioindiawest": 0,
		"korea": 0,
		"koreacentral": 0,
		"koreasouth": 0,
		"northcentralus": 572.43357094,
		"northcentralusstage": 0,
		"northeurope": 542.95006689,
		"norway": 455,
		"norwayeast": 0,
		"norwaywest": 0,
		"southafrica": 0,
		"southafricanorth": 0,
		"southafricawest": 0,
		"southcentralus": 498.49801463,
		"southcentralusstage": 0,
		"southeastasia": 0,
		"southeastasiastage": 0,
		"southindia": 0,
		"swedencentral": 0,
		"switzerland": 0,
		"switzerlandnorth": 0,
		"switzerlandwest": 0,
		"uae": 0,
		"uaecentral": 0,
		"uaenorth": 0,
		"uk": 0,
		"uksouth": 434.08789809,
		"ukwest": 434.08789809,
		"unitedstates": 0,
		"unitedstateseuap": 0,
		"westcentralus": 698.07865743,
		"westeurope": 0,
		"westindia": 0,
		"westus": 358.79156467,
		"westus2": 258.09405853,
		"westus2stage": 0,
		"westus3": 514.37374758,
		"westusstage": 0
	},
	"startDate": "2023-06-27T17:53:18.899440614Z",
	"userId": ""
}
