{
	"createdDate": "2023-04-09T21:18:44.232064356Z",
	"endDate": "2023-04-09T21:23:18.912103657Z",
	"id": "report",
	"intensities": {
		"asia": 0,
		"asiapacific": 0,
		"australia": 0,
		"australiacentral": 814.19830415,
		"australiacentral2": 814.19830415,
		"australiaeast": 814.19830415,
		"australiasoutheast": 806.94082623,
		"brazil": 0,
		"brazilsouth": 0,
		"brazilsoutheast": 0,
		"canada": 0,
		"canadacentral": 482.62228168,
		"canadaeast": 461.75703266000005,
		"centralindia": 0,
		"centralus": 581.50541834,
		"centraluseuap": 581.50541834,
		"centralusstage": 0,
		"eastasia": 0,
		"eastasiastage": 0,
		"eastus": 351.98767912,
		"eastus2": 355.61641808,
		"eastus2euap": 355.61641808,
		"eastus2stage": 0,
		"eastusstage": 0,
		"europe": 0,
		"france": 0,
		"francecentral": 0,
		"francesouth": 0,
		"germany": 0,
		"germanynorth": 809.2087880800001,
		"germanywestcentral": 809.2087880800001,
		"global": 0,
		"india": 0,
		"japan": 0,
		"japaneast": 0,
		"japanwest": 0,
		"jioindiacentral": 0,
		"jioindiawest": 0,
		"korea": 0,
		"koreacentral": 0,
		"koreasouth": 0,
		"northcentralus": 36.287389600000004,
		"northcentralusstage": 0,
		"northeurope": 524.8063720900001,
		"norway": 438,
		"norwayeast": 0,
		"norwaywest": 0,
		"southafrica": 0,
		"southafricanorth": 0,
		"southafricawest": 0,
		"southcentralus": 579.23745649,
		"southcentralusstage": 0,
		"southeastasia": 0,
		"southeastasiastage": 0,
		"southindia": 0,
		"swedencentral": 0,
		"switzerland": 0,
		"switzerlandnorth": 0,
		"switzerlandwest": 0,
		"uae": 0,
		"uaecentral": 0,
		"uaenorth": 0,
		"uk": 0,
		"uksouth": 417.75857277,
		"ukwest": 417.75857277,
		"unitedstates": 0,
		"unitedstateseuap": 0,
		"westcentralus": 734.36604703,
		"westeurope": 0,
		"westindia": 0,
		"westus": 23.586803240000002,
		"westus2": 526.1671492,
		"westus2stage": 0,
		"westus3": 576.96949464,
		"westusstage": 0
	},
	"startDate": "2023-04-09T21:18:18.912103583Z",
	"userId": ""
}
